LICENSE.txt
README.md
setup.py
soufyane_rocket/__init__.py
soufyane_rocket.egg-info/PKG-INFO
soufyane_rocket.egg-info/SOURCES.txt
soufyane_rocket.egg-info/dependency_links.txt
soufyane_rocket.egg-info/requires.txt
soufyane_rocket.egg-info/top_level.txt