Metadata-Version: 2.1
Name: soufyane_rocket
Version: 1.0.0
Summary: An awesome package that does something
Home-page: http://pypi.python.org/pypi/soufyane_rocket/
Author: soufyane
Author-email: s.belmana@esi-sba.dz
License: LICENSE.txt
License-File: LICENSE.txt
Requires-Dist: soufyane_rocket
